AUTHORS.rst
CONTRIBUTING.rst
HISTORY.rst
LICENSE
MANIFEST.in
README.rst
setup.cfg
setup.py
bayescache/__init__.py
bayescache/launch.py
bayescache.egg-info/PKG-INFO
bayescache.egg-info/SOURCES.txt
bayescache.egg-info/dependency_links.txt
bayescache.egg-info/not-zip-safe
bayescache.egg-info/top_level.txt
test/test_bayescache.py